README.txt
setup.py
collective/__init__.py
collective.collage.contentleadimage.egg-info/PKG-INFO
collective.collage.contentleadimage.egg-info/SOURCES.txt
collective.collage.contentleadimage.egg-info/dependency_links.txt
collective.collage.contentleadimage.egg-info/entry_points.txt
collective.collage.contentleadimage.egg-info/namespace_packages.txt
collective.collage.contentleadimage.egg-info/not-zip-safe
collective.collage.contentleadimage.egg-info/requires.txt
collective.collage.contentleadimage.egg-info/top_level.txt
collective/collage/__init__.py
collective/collage/contentleadimage/__init__.py
collective/collage/contentleadimage/browser.py
collective/collage/contentleadimage/configure.zcml
collective/collage/contentleadimage/templates/content_leadimage_folder_summary.pt
collective/collage/contentleadimage/templates/content_leadimage_topic_summary.pt
docs/AUTHORS.txt
docs/HISTORY.txt
docs/INSTALL.txt
docs/LICENSE.GPL
docs/LICENSE.txt