Metadata-Version: 1.0
Name: collective.collage.contentleadimage
Version: 0.1
Summary: Views for Products.Collage that display content with images from collective.contentleadimage
Home-page: https://svn.plone.org/svn/collective/Products.Collage/addons/collective.collage.contentleadimage
Author: JCU eResearch Centre
Author-email: eresearch@jcu.edu.au
License: GPL
Keywords: plone collage contentleadimage view image
Platform: UNKNOWN
Classifier: Framework :: Plone
Classifier: Programming Language :: Python
